AUTHORS
LICENSE
MANIFEST.in
NOTICE
README.md
pyproject.toml
requirements.txt
setup.py
typed_python/AllTypes.hpp
typed_python/AlternativeMatcherType.hpp
typed_python/AlternativeType.cpp
typed_python/AlternativeType.hpp
typed_python/BoundMethodType.hpp
typed_python/BytesType.cpp
typed_python/BytesType.hpp
typed_python/ClassType.cpp
typed_python/ClassType.hpp
typed_python/Codebase.py
typed_python/Codebase_test.py
typed_python/CompositeType.cpp
typed_python/CompositeType.hpp
typed_python/ConcreteAlternativeType.cpp
typed_python/ConcreteAlternativeType.hpp
typed_python/ConstDictType.cpp
typed_python/ConstDictType.hpp
typed_python/ConversionLevel.hpp
typed_python/DeepcopyContext.hpp
typed_python/DeserializationBuffer.cpp
typed_python/DeserializationBuffer.hpp
typed_python/DictType.cpp
typed_python/DictType.hpp
typed_python/EmbeddedMessageType.hpp
typed_python/Format.hpp
typed_python/ForwardType.hpp
typed_python/FunctionCallArgMapping.hpp
typed_python/FunctionType.cpp
typed_python/FunctionType.hpp
typed_python/HashAccumulator.hpp
typed_python/HeldClassType.cpp
typed_python/HeldClassType.hpp
typed_python/Instance.cpp
typed_python/Instance.hpp
typed_python/Memory.cpp
typed_python/Memory.hpp
typed_python/ModuleRepresentation.hpp
typed_python/ModuleRepresentationCopyContext.hpp
typed_python/MutuallyRecursiveTypeGroup.cpp
typed_python/MutuallyRecursiveTypeGroup.hpp
typed_python/NoneType.hpp
typed_python/NullSerializationContext.hpp
typed_python/OneOfType.cpp
typed_python/OneOfType.hpp
typed_python/PointerToType.hpp
typed_python/PromotesTo.hpp
typed_python/PyAlternativeInstance.cpp
typed_python/PyAlternativeInstance.hpp
typed_python/PyAlternativeMatcherInstance.hpp
typed_python/PyBoundMethodInstance.cpp
typed_python/PyBoundMethodInstance.hpp
typed_python/PyBytesInstance.hpp
typed_python/PyCellType.hpp
typed_python/PyClassInstance.cpp
typed_python/PyClassInstance.hpp
typed_python/PyCompositeTypeInstance.cpp
typed_python/PyCompositeTypeInstance.hpp
typed_python.egg-info/PKG-INFO
typed_python.egg-info/SOURCES.txt
typed_python.egg-info/dependency_links.txt
typed_python.egg-info/not-zip-safe
typed_python.egg-info/requires.txt
typed_python.egg-info/top_level.txt
