Metadata-Version: 1.2
Name: typed-python
Version: 0.2.5
Summary: opt-in strong typing at runtime for python, plus a compiler.
Home-page: https://github.com/aprioriinvestments/typed_python
Author: Braxton Mckee
Author-email: braxton.mckee@gmail.com
License: Apache Software License v2.0
Platform: UNKNOWN
Classifier: License :: OSI Approved :: Apache Software License
Classifier: Programming Language :: Python :: 3 :: Only
Requires-Python: >=3.7
